tedx_flow/__init__.py
tedx_flow/context.py
tedx_flow/flow.py
tedx_flow/py.typed
tedx_flow/state.py
tedx_flow-0.1.0.dist-info/licenses/LICENSE
tedx_flow-0.1.0.dist-info/METADATA
tedx_flow-0.1.0.dist-info/WHEEL
tedx_flow-0.1.0.dist-info/top_level.txt
tedx_flow-0.1.0.dist-info/RECORD
